[
  {
    "inputs": [
      { "internalType": "address", "name": "_tkn1", "type": "address" },
      { "internalType": "address", "name": "_nft", "type": "address" },
      { "internalType": "address", "name": "_tkn2", "type": "address" }
    ],
    "stateMutability": "nonpayable",
    "type": "constructor"
  },
  {
    "anonymous": false,
    "inputs": [
      {
        "indexed": false,
        "internalType": "address",
        "name": "user",
        "type": "address"
      },
      {
        "indexed": false,
        "internalType": "uint256",
        "name": "amount",
        "type": "uint256"
      },
      {
        "indexed": false,
        "internalType": "uint256",
        "name": "_nftId1",
        "type": "uint256"
      },
      {
        "indexed": false,
        "internalType": "uint256",
        "name": "_nftId2",
        "type": "uint256"
      }
    ],
    "name": "CandidateLockedAssets",
    "type": "event"
  },
  {
    "anonymous": false,
    "inputs": [
      {
        "indexed": false,
        "internalType": "address",
        "name": "user",
        "type": "address"
      },
      {
        "indexed": false,
        "internalType": "uint256",
        "name": "amount",
        "type": "uint256"
      },
      {
        "indexed": false,
        "internalType": "uint256",
        "name": "_nftId",
        "type": "uint256"
      }
    ],
    "name": "VoterLockedAssets",
    "type": "event"
  },
  {
    "anonymous": false,
    "inputs": [
      {
        "indexed": false,
        "internalType": "address",
        "name": "C_Addr",
        "type": "address"
      },
      {
        "indexed": false,
        "internalType": "string",
        "name": "C_Name",
        "type": "string"
      },
      {
        "indexed": false,
        "internalType": "string",
        "name": "description",
        "type": "string"
      },
      {
        "indexed": false,
        "internalType": "uint256",
        "name": "time",
        "type": "uint256"
      },
      {
        "indexed": false,
        "internalType": "uint256",
        "name": "voteCount",
        "type": "uint256"
      },
      {
        "indexed": false,
        "internalType": "bool",
        "name": "IsApproved",
        "type": "bool"
      }
    ],
    "name": "eveProposal",
    "type": "event"
  },
  {
    "anonymous": false,
    "inputs": [
      {
        "indexed": false,
        "internalType": "address",
        "name": "voter",
        "type": "address"
      },
      {
        "indexed": false,
        "internalType": "uint256",
        "name": "index",
        "type": "uint256"
      }
    ],
    "name": "eveVote",
    "type": "event"
  },
  {
    "inputs": [
      { "internalType": "uint256", "name": "proposalIndex", "type": "uint256" }
    ],
    "name": "CandidateAddress",
    "outputs": [{ "internalType": "address", "name": "", "type": "address" }],
    "stateMutability": "view",
    "type": "function"
  },
  {
    "inputs": [
      { "internalType": "uint256", "name": "proposalIndex", "type": "uint256" }
    ],
    "name": "CandidateName",
    "outputs": [{ "internalType": "string", "name": "", "type": "string" }],
    "stateMutability": "view",
    "type": "function"
  },
  {
    "inputs": [
      { "internalType": "uint256", "name": "proposalIndex", "type": "uint256" }
    ],
    "name": "CandidateVote",
    "outputs": [{ "internalType": "uint256", "name": "", "type": "uint256" }],
    "stateMutability": "view",
    "type": "function"
  },
  {
    "inputs": [
      { "internalType": "uint256", "name": "_tknAmount", "type": "uint256" },
      { "internalType": "uint256", "name": "_nftId1", "type": "uint256" },
      { "internalType": "uint256", "name": "_nftId2", "type": "uint256" }
    ],
    "name": "LockForCandidate",
    "outputs": [],
    "stateMutability": "nonpayable",
    "type": "function"
  },
  {
    "inputs": [
      { "internalType": "uint256", "name": "_tknAmount", "type": "uint256" },
      { "internalType": "uint256", "name": "_nftId", "type": "uint256" }
    ],
    "name": "LockForVoter",
    "outputs": [],
    "stateMutability": "nonpayable",
    "type": "function"
  },
  {
    "inputs": [
      { "internalType": "uint256", "name": "proposalIndex", "type": "uint256" }
    ],
    "name": "ProposalDescription",
    "outputs": [{ "internalType": "string", "name": "", "type": "string" }],
    "stateMutability": "view",
    "type": "function"
  },
  {
    "inputs": [],
    "name": "balanceOf",
    "outputs": [{ "internalType": "uint256", "name": "", "type": "uint256" }],
    "stateMutability": "view",
    "type": "function"
  },
  {
    "inputs": [],
    "name": "claimAssets",
    "outputs": [],
    "stateMutability": "nonpayable",
    "type": "function"
  },
  {
    "inputs": [],
    "name": "erc20TokenAddress",
    "outputs": [{ "internalType": "address", "name": "", "type": "address" }],
    "stateMutability": "view",
    "type": "function"
  },
  {
    "inputs": [],
    "name": "erc20TokenAddress2",
    "outputs": [{ "internalType": "address", "name": "", "type": "address" }],
    "stateMutability": "view",
    "type": "function"
  },
  {
    "inputs": [],
    "name": "getProposalCount",
    "outputs": [{ "internalType": "uint256", "name": "", "type": "uint256" }],
    "stateMutability": "view",
    "type": "function"
  },
  {
    "inputs": [],
    "name": "getUserLockedTokens",
    "outputs": [{ "internalType": "uint256", "name": "", "type": "uint256" }],
    "stateMutability": "view",
    "type": "function"
  },
  {
    "inputs": [],
    "name": "getUserNFTs",
    "outputs": [{ "internalType": "uint256", "name": "", "type": "uint256" }],
    "stateMutability": "view",
    "type": "function"
  },
  {
    "inputs": [],
    "name": "getUserTokens",
    "outputs": [{ "internalType": "uint256", "name": "", "type": "uint256" }],
    "stateMutability": "view",
    "type": "function"
  },
  {
    "inputs": [],
    "name": "lockedToken",
    "outputs": [{ "internalType": "uint256", "name": "", "type": "uint256" }],
    "stateMutability": "view",
    "type": "function"
  },
  {
    "inputs": [{ "internalType": "address", "name": "", "type": "address" }],
    "name": "mapCandidateLockedAssets",
    "outputs": [{ "internalType": "bool", "name": "", "type": "bool" }],
    "stateMutability": "view",
    "type": "function"
  },
  {
    "inputs": [{ "internalType": "address", "name": "", "type": "address" }],
    "name": "mapVoterLockedAssets",
    "outputs": [{ "internalType": "bool", "name": "", "type": "bool" }],
    "stateMutability": "view",
    "type": "function"
  },
  {
    "inputs": [{ "internalType": "address", "name": "", "type": "address" }],
    "name": "maplockasset",
    "outputs": [
      { "internalType": "uint256", "name": "Lock_Period", "type": "uint256" },
      { "internalType": "uint256", "name": "Tkn_Amount", "type": "uint256" },
      { "internalType": "uint256", "name": "Nft_id1", "type": "uint256" },
      { "internalType": "uint256", "name": "Nft_id2", "type": "uint256" }
    ],
    "stateMutability": "view",
    "type": "function"
  },
  {
    "inputs": [],
    "name": "nftAddress",
    "outputs": [{ "internalType": "address", "name": "", "type": "address" }],
    "stateMutability": "view",
    "type": "function"
  },
  {
    "inputs": [{ "internalType": "uint256", "name": "", "type": "uint256" }],
    "name": "proposals",
    "outputs": [
      { "internalType": "address", "name": "candidateAddr", "type": "address" },
      { "internalType": "string", "name": "C_Name", "type": "string" },
      { "internalType": "string", "name": "description", "type": "string" },
      { "internalType": "uint256", "name": "time", "type": "uint256" },
      { "internalType": "uint256", "name": "voteCount", "type": "uint256" },
      { "internalType": "bool", "name": "isApproved", "type": "bool" }
    ],
    "stateMutability": "view",
    "type": "function"
  },
  {
    "inputs": [],
    "name": "totalLockedToken",
    "outputs": [{ "internalType": "uint256", "name": "", "type": "uint256" }],
    "stateMutability": "view",
    "type": "function"
  },
  {
    "inputs": [{ "internalType": "address", "name": "", "type": "address" }],
    "name": "voters",
    "outputs": [{ "internalType": "bool", "name": "", "type": "bool" }],
    "stateMutability": "view",
    "type": "function"
  }
]
